chariothy_common/__init__.py
chariothy_common/app_tool.py
chariothy_common/config_sample.py
chariothy_common/exception.py
chariothy_common/get_ch.py
chariothy_common/utils.py
chariothy_common-1.3.2.dist-info/LICENSE
chariothy_common-1.3.2.dist-info/METADATA
chariothy_common-1.3.2.dist-info/WHEEL
chariothy_common-1.3.2.dist-info/top_level.txt
chariothy_common-1.3.2.dist-info/RECORD
