Metadata-Version: 2.1
Name: chariothy-common
Version: 1.3.2
Summary: Common code for myself.
Home-page: https://github.com/chariothy/pycommon.git
Author: Henry TIAN
Author-email: chariothy@gmail.com
License: MIT
Platform: UNKNOWN
Classifier: License :: OSI Approved :: MIT License
Classifier: Programming Language :: Python
Classifier: Programming Language :: Python :: 3.6
Classifier: Programming Language :: Python :: Implementation :: CPython
Requires-Python: >=3.6.0
